morphemes/__init__.py
morphemes/cli/__init__.py
morphemes/config/__init__.py
morphemes/utilities/__init__.py
morphemes/utilities/morpheme_database/__init__.py
morphemes-1.2.0.dist-info/LICENSE
morphemes-1.2.0.dist-info/LICENSE.txt
morphemes-1.2.0.dist-info/METADATA
morphemes-1.2.0.dist-info/WHEEL
morphemes-1.2.0.dist-info/entry_points.txt
morphemes-1.2.0.dist-info/top_level.txt
morphemes-1.2.0.dist-info/RECORD
