Metadata-Version: 2.1
Name: morphemes
Version: 1.2.0
Summary: A practical Python Library for identifying morphemes in the english language.
Home-page: https://github.com/ecscstatsconsulting/morphemes
Author: Enkeleda Cuko & Paul Warren
Author-email: ecsctechdepartment@gmail.com
License: MIT
Project-URL: Documentation, https://github.com/ecscstatsconsulting/morphemes#readme
Project-URL: Source, https://github.com/ecscstatsconsulting/morphemes
Project-URL: Tracker, https://github.com/ecscstatsconsulting/morphemes/issues
Keywords: morpheme,morphology,nlp
License-File: LICENSE
License-File: LICENSE.txt
Requires-Dist: pandas (>=1.4.1)
Requires-Dist: requests (>=2.27.1)
Requires-Dist: tinydb (>=4.7.0)
Requires-Dist: openpyxl (>=3.0.9)
Requires-Dist: click (>=8.0.3)
Requires-Dist: appdata (>=2.1.2)
Requires-Dist: tabulate (>=0.9.0)
Requires-Dist: asciitree (>=0.3.3)
